Workbook

Sheet Assumptions
A1: Master Assumptions
A3: COMPANY PROFILE
A4: Parameter | B4: Value | C4: Unit | D4: Min | E4: Max
A5: Company Name | B5: Apex Dynamics Inc | C5: text
A6: Ticker Symbol | B6: APDX | C6: text
A7: Fiscal Year Start | B7: Jan | C7: month
A8: Base Revenue ($M) | B8: 85.4 | C8: $M | D8: 10 | E8: 500
A9: Headcount | B9: 342 | C9: people | D9: 50 | E9: 2000
A10: Founded Year | B10: 2008 | C10: year | D10: 1900 | E10: 2030
A12: FINANCIAL ASSUMPTIONS
A13: Parameter | B13: Value | C13: Unit | D13: Min | E13: Max
A14: Revenue Growth Rate | B14: 0.082 | C14: % | D14: 0 | E14: 0.3
A15: Gross Margin | B15: 0.615 | C15: % | D15: 0.2 | E15: 0.9
A16: OpEx % Revenue | B16: 0.34 | C16: % | D16: 0.1 | E16: 0.6
A17: EBITDA Margin | B17: 0.221 | C17: % | D17: 0.05 | E17: 0.5
A18: Tax Rate | B18: 0.21 | C18: % | D18: 0 | E18: 0.4
A19: Discount Rate (WACC) | B19: 0.095 | C19: % | D19: 0.04 | E19: 0.2
A20: Terminal Growth Rate | B20: 0.025 | C20: % | D20: 0 | E20: 0.05
A21: Inflation Assumption | B21: 0.028 | C21: % | D21: 0 | E21: 0.1
A22: D&A % Revenue | B22: 0.042 | C22: % | D22: 0.01 | E22: 0.1
A23: Capex % Revenue | B23: 0.065 | C23: % | D23: 0.02 | E23: 0.15
A25: SCENARIO SELECTOR
A26: Parameter | B26: Value | C26: Unit | D26: Bear | E26: Bull
A27: Active Scenario (1-3) | B27: 2 | C27: 1=Bear 2=Base 3=Bull | D27: 1 | E27: 3
A28: Bear Growth Rate | B28: 0.02 | C28: %
A29: Base Growth Rate | B29: 0.082 | C29: %
A30: Bull Growth Rate | B30: 0.145 | C30: %
A31: Active Growth Rate | B31: =IFERROR(CHOOSE(B27,B28,B29,B30),B29) | C31: %
A33: ASSUMPTION VALIDATION
A34: Check | B34: Status | C34: Formula Logic | D34: Expected | E34: Actual
A35: Scenario Valid | B35: =IF(AND(B27>=1,B27<=3),"✔ OK","✘ Out of range") | C35: AND(B27>=1,B27<=3) | D35: 1–3 | E35: =TEXT(B27,"0")
A36: Company Name Filled | B36: =IF(ISBLANK(B5),"✘ Missing","✔ OK") | C36: ISBLANK | D36: Non-empty | E36: =IF(ISBLANK(B5),"empty",LEFT(B5,12))
A37: Ticker is Text | B37: =IF(ISTEXT(B6),"✔ OK","✘ Not text") | C37: ISTEXT | D37: Text string | E37: =B6
A38: Growth in Range | B38: =IF(AND(B14>=D14,B14<=E14),"✔ OK","✘ Out of range") | C38: AND with bounds | D38: 0%–30% | E38: =TEXT(B14,"0.0%")
A39: Discount > Terminal | B39: =IF(B19>B20,"✔ OK","✘ Check rates") | C39: Simple comparison | D39: WACC > TGR | E39: =TEXT(B19-B20,"0.0%")
A40: Tax Rate Valid | B40: =IF(OR(B18<0,B18>0.5),"✘ Unusual","✔ OK") | C40: OR out-of-bounds | D40: 0%–50% | E40: =TEXT(B18,"0.0%")

Sheet Revenue Model
A1: 📊 7-Year Revenue & Profitability Model
B3: PROJECTED FISCAL YEARS ($M)
A4: Line Item | B4: 2024 | C4: 2025 | D4: 2026 | E4: 2027 | F4: 2028 | G4: 2029 | H4: 2030
A5: ── REVENUE ──
A6: Base Revenue ($M) | B6: =Assumptions!B8 | C6: =B8 | D6: =C8 | E6: =D8 | F6: =E8 | G6: =F8 | H6: =G8
A7: YoY Growth Rate | B7: =Assumptions!B31 | C7: =Assumptions!B31 | D7: =Assumptions!B31 | E7: =Assumptions!B31 | F7: =Assumptions!B31 | G7: =Assumptions!B31 | H7: =Assumptions!B31
A8: Revenue ($M) | B8: =B6 | C8: =ROUND(B8*(1+C7),2) | D8: =ROUND(C8*(1+D7),2) | E8: =ROUND(D8*(1+E7),2) | F8: =ROUND(E8*(1+F7),2) | G8: =ROUND(F8*(1+G7),2) | H8: =ROUND(G8*(1+H7),2)
A9: ── PROFITABILITY ──
A10: Gross Profit ($M) | B10: =ROUND(B8*Assumptions!$B$15,2) | C10: =ROUND(C8*Assumptions!$B$15,2) | D10: =ROUND(D8*Assumptions!$B$15,2) | E10: =ROUND(E8*Assumptions!$B$15,2) | F10: =ROUND(F8*Assumptions!$B$15,2) | G10: =ROUND(G8*Assumptions!$B$15,2) | H10: =ROUND(H8*Assumptions!$B$15,2)
A11: Gross Margin % | B11: =IFERROR(B10/B8,0) | C11: =IFERROR(C10/C8,0) | D11: =IFERROR(D10/D8,0) | E11: =IFERROR(E10/E8,0) | F11: =IFERROR(F10/F8,0) | G11: =IFERROR(G10/G8,0) | H11: =IFERROR(H10/H8,0)
A12: Operating Expenses ($M) | B12: =ROUND(B8*Assumptions!$B$16,2) | C12: =ROUND(C8*Assumptions!$B$16,2) | D12: =ROUND(D8*Assumptions!$B$16,2) | E12: =ROUND(E8*Assumptions!$B$16,2) | F12: =ROUND(F8*Assumptions!$B$16,2) | G12: =ROUND(G8*Assumptions!$B$16,2) | H12: =ROUND(H8*Assumptions!$B$16,2)
A13: EBITDA ($M) | B13: =B10-B12 | C13: =C10-C12 | D13: =D10-D12 | E13: =E10-E12 | F13: =F10-F12 | G13: =G10-G12 | H13: =H10-H12
A14: EBITDA Margin % | B14: =IFERROR(B13/B8,0) | C14: =IFERROR(C13/C8,0) | D14: =IFERROR(D13/D8,0) | E14: =IFERROR(E13/E8,0) | F14: =IFERROR(F13/F8,0) | G14: =IFERROR(G13/G8,0) | H14: =IFERROR(H13/H8,0)
A15: D&A ($M) | B15: =ROUND(B8*Assumptions!$B$22,2) | C15: =ROUND(C8*Assumptions!$B$22,2) | D15: =ROUND(D8*Assumptions!$B$22,2) | E15: =ROUND(E8*Assumptions!$B$22,2) | F15: =ROUND(F8*Assumptions!$B$22,2) | G15: =ROUND(G8*Assumptions!$B$22,2) | H15: =ROUND(H8*Assumptions!$B$22,2)
A16: EBIT ($M) | B16: =B13-B15 | C16: =C13-C15 | D16: =D13-D15 | E16: =E13-E15 | F16: =F13-F15 | G16: =G13-G15 | H16: =H13-H15
A17: EBIT Margin % | B17: =IFERROR(B16/B8,0) | C17: =IFERROR(C16/C8,0) | D17: =IFERROR(D16/D8,0) | E17: =IFERROR(E16/E8,0) | F17: =IFERROR(F16/F8,0) | G17: =IFERROR(G16/G8,0) | H17: =IFERROR(H16/H8,0)
A18: Tax Expense ($M) | B18: =IF(B16>0,ROUND(B16*Assumptions!$B$18,2),0) | C18: =IF(C16>0,ROUND(C16*Assumptions!$B$18,2),0) | D18: =IF(D16>0,ROUND(D16*Assumptions!$B$18,2),0) | E18: =IF(E16>0,ROUND(E16*Assumptions!$B$18,2),0) | F18: =IF(F16>0,ROUND(F16*Assumptions!$B$18,2),0) | G18: =IF(G16>0,ROUND(G16*Assumptions!$B$18,2),0) | H18: =IF(H16>0,ROUND(H16*Assumptions!$B$18,2),0)
A19: Net Income ($M) | B19: =B16-B18 | C19: =C16-C18 | D19: =D16-D18 | E19: =E16-E18 | F19: =F16-F18 | G19: =G16-G18 | H19: =H16-H18
A20: Net Margin % | B20: =IFERROR(B19/B8,0) | C20: =IFERROR(C19/C8,0) | D20: =IFERROR(D19/D8,0) | E20: =IFERROR(E19/E8,0) | F20: =IFERROR(F19/F8,0) | G20: =IFERROR(G19/G8,0) | H20: =IFERROR(H19/H8,0)
A21: ── CASH FLOW ──
A22: D&A Add-back | B22: =B15 | C22: =C15 | D22: =D15 | E22: =E15 | F22: =F15 | G22: =G15 | H22: =H15
A23: Capex ($M) | B23: =-ROUND(B8*Assumptions!$B$23,2) | C23: =-ROUND(C8*Assumptions!$B$23,2) | D23: =-ROUND(D8*Assumptions!$B$23,2) | E23: =-ROUND(E8*Assumptions!$B$23,2) | F23: =-ROUND(F8*Assumptions!$B$23,2) | G23: =-ROUND(G8*Assumptions!$B$23,2) | H23: =-ROUND(H8*Assumptions!$B$23,2)
A24: Free Cash Flow ($M) | B24: =B19+B22+B23 | C24: =C19+C22+C23 | D24: =D19+D22+D23 | E24: =E19+E22+E23 | F24: =F19+F22+F23 | G24: =G19+G22+G23 | H24: =H19+H22+H23
A27: SUMMARY STATISTICS
A28: Metric | B28: Value | C28: Formula Used | D28: Notes
A29: Total 7-Yr Revenue | B29: =SUM(B8:H8) | C29: SUM
A30: AVERAGE Annual Revenue | B30: =AVERAGE(B8:H8) | C30: AVERAGE
A31: Max Revenue Year | B31: =MAX(B8:H8) | C31: MAX
A32: Min Revenue Year | B32: =MIN(B8:H8) | C32: MIN
A33: Revenue Std Dev | B33: =STDEV(B8:H8) | C33: STDEV
A34: Rev CAGR (7yr) | B34: =IFERROR((H8/B8)^(1/6)-1,0) | C34: Math
A35: NPV of FCF | B35: =IFERROR(NPV(Assumptions!B19,C24:H24)+B24,0) | C35: NPV
A36: Avg EBITDA Margin | B36: =IFERROR(AVERAGE(B14:H14),0) | C36: AVERAGE
A37: Best Net Margin Yr | B37: =TEXT(INDEX(B4:H4,MATCH(MAX(B20:H20),B20:H20,0)),"0") | C37: INDEX+MATCH+TEXT
A38: Total Net Income | B38: =SUM(B19:H19) | C38: SUM
A39: Count Profitable Yrs | B39: =COUNTIF(B19:H19,">0") | C39: COUNTIF
A40: Top 3 FCF Average | B40: =IFERROR((LARGE(B24:H24,1)+LARGE(B24:H24,2)+LARGE(B24:H24,3))/3,0) | C40: LARGE

Sheet Employee Directory
A1: 👥 Employee Directory & Analytics
A3: EMPLOYEE MASTER TABLE
A4: Emp ID | B4: First | C4: Last | D4: Full Name | E4: Dept | F4: Title | G4: Salary | H4: Start Date | I4: Yrs Tenure | J4: Grade | K4: Status | L4: Email
A5: E001 | B5: Sarah | C5: Chen | D5: =CONCATENATE(B5," ",C5) | E5: Engineering | F5: Sr Engineer | G5: 112000 | H5: 2018-03-15 | I5: =ROUNDDOWN((TODAY()-H5)/365.25,1) | J5: A | K5: =IF(I5<1,"New",IF(I5<3,"Junior",IF(I5<7,"Mid","Senior"))) | L5: =LOWER(CONCATENATE(LEFT(B5,1),C5,"@apexdynamics.com"))
A6: E002 | B6: Marcus | C6: Williams | D6: =CONCATENATE(B6," ",C6) | E6: Finance | F6: Analyst | G6: 68000 | H6: 2021-07-01 | I6: =ROUNDDOWN((TODAY()-H6)/365.25,1) | J6: B | K6: =IF(I6<1,"New",IF(I6<3,"Junior",IF(I6<7,"Mid","Senior"))) | L6: =LOWER(CONCATENATE(LEFT(B6,1),C6,"@apexdynamics.com"))
A7: E003 | B7: Priya | C7: Patel | D7: =CONCATENATE(B7," ",C7) | E7: Engineering | F7: Lead Engineer | G7: 138000 | H7: 2015-11-20 | I7: =ROUNDDOWN((TODAY()-H7)/365.25,1) | J7: A | K7: =IF(I7<1,"New",IF(I7<3,"Junior",IF(I7<7,"Mid","Senior"))) | L7: =LOWER(CONCATENATE(LEFT(B7,1),C7,"@apexdynamics.com"))
A8: E004 | B8: James | C8: O'Brien | D8: =CONCATENATE(B8," ",C8) | E8: Sales | F8: Account Exec | G8: 82000 | H8: 2020-02-14 | I8: =ROUNDDOWN((TODAY()-H8)/365.25,1) | J8: B | K8: =IF(I8<1,"New",IF(I8<3,"Junior",IF(I8<7,"Mid","Senior"))) | L8: =LOWER(CONCATENATE(LEFT(B8,1),C8,"@apexdynamics.com"))
A9: E005 | B9: Aisha | C9: Johnson | D9: =CONCATENATE(B9," ",C9) | E9: HR | F9: HR Manager | G9: 91000 | H9: 2017-06-30 | I9: =ROUNDDOWN((TODAY()-H9)/365.25,1) | J9: A | K9: =IF(I9<1,"New",IF(I9<3,"Junior",IF(I9<7,"Mid","Senior"))) | L9: =LOWER(CONCATENATE(LEFT(B9,1),C9,"@apexdynamics.com"))
A10: E006 | B10: Thomas | C10: Schmidt | D10: =CONCATENATE(B10," ",C10) | E10: Engineering | F10: Engineer | G10: 95000 | H10: 2019-09-10 | I10: =ROUNDDOWN((TODAY()-H10)/365.25,1) | J10: B | K10: =IF(I10<1,"New",IF(I10<3,"Junior",IF(I10<7,"Mid","Senior"))) | L10: =LOWER(CONCATENATE(LEFT(B10,1),C10,"@apexdynamics.com"))
A11: E007 | B11: Mei | C11: Liu | D11: =CONCATENATE(B11," ",C11) | E11: Finance | F11: Sr Analyst | G11: 78000 | H11: 2022-01-15 | I11: =ROUNDDOWN((TODAY()-H11)/365.25,1) | J11: B | K11: =IF(I11<1,"New",IF(I11<3,"Junior",IF(I11<7,"Mid","Senior"))) | L11: =LOWER(CONCATENATE(LEFT(B11,1),C11,"@apexdynamics.com"))
A12: E008 | B12: Carlos | C12: Rivera | D12: =CONCATENATE(B12," ",C12) | E12: Sales | F12: Sales Dir | G12: 125000 | H12: 2016-04-05 | I12: =ROUNDDOWN((TODAY()-H12)/365.25,1) | J12: A | K12: =IF(I12<1,"New",IF(I12<3,"Junior",IF(I12<7,"Mid","Senior"))) | L12: =LOWER(CONCATENATE(LEFT(B12,1),C12,"@apexdynamics.com"))
A13: E009 | B13: Fatima | C13: Al-Hassan | D13: =CONCATENATE(B13," ",C13) | E13: Engineering | F13: Principal Eng | G13: 158000 | H13: 2013-08-22 | I13: =ROUNDDOWN((TODAY()-H13)/365.25,1) | J13: A | K13: =IF(I13<1,"New",IF(I13<3,"Junior",IF(I13<7,"Mid","Senior"))) | L13: =LOWER(CONCATENATE(LEFT(B13,1),C13,"@apexdynamics.com"))
A14: E010 | B14: Derek | C14: Thompson | D14: =CONCATENATE(B14," ",C14) | E14: Marketing | F14: CMO | G14: 175000 | H14: 2012-01-10 | I14: =ROUNDDOWN((TODAY()-H14)/365.25,1) | J14: A | K14: =IF(I14<1,"New",IF(I14<3,"Junior",IF(I14<7,"Mid","Senior"))) | L14: =LOWER(CONCATENATE(LEFT(B14,1),C14,"@apexdynamics.com"))
A15: E011 | B15: Yuki | C15: Tanaka | D15: =CONCATENATE(B15," ",C15) | E15: Engineering | F15: Engineer | G15: 88000 | H15: 2023-03-01 | I15: =ROUNDDOWN((TODAY()-H15)/365.25,1) | J15: C | K15: =IF(I15<1,"New",IF(I15<3,"Junior",IF(I15<7,"Mid","Senior"))) | L15: =LOWER(CONCATENATE(LEFT(B15,1),C15,"@apexdynamics.com"))
A16: E012 | B16: Bria | C16: Foster | D16: =CONCATENATE(B16," ",C16) | E16: HR | F16: Recruiter | G16: 62000 | H16: 2022-11-15 | I16: =ROUNDDOWN((TODAY()-H16)/365.25,1) | J16: C | K16: =IF(I16<1,"New",IF(I16<3,"Junior",IF(I16<7,"Mid","Senior"))) | L16: =LOWER(CONCATENATE(LEFT(B16,1),C16,"@apexdynamics.com"))
... A24: E020 | B24: Amara | C24: Diallo | D24: =CONCATENATE(B24," ",C24) | E24: Marketing | F24: Analyst | G24: 65000 | H24: 2023-06-12 | I24: =ROUNDDOWN((TODAY()-H24)/365.25,1) | J24: C | K24: =IF(I24<1,"New",IF(I24<3,"Junior",IF(I24<7,"Mid","Senior"))) | L24: =LOWER(CONCATENATE(LEFT(B24,1),C24,"@apexdynamics.com"))
A26: WORKFORCE ANALYTICS
A27: Metric | B27: Value | C27: Formula | D27: Scope
A28: Total Headcount | B28: =COUNTA(A5:A24) | C28: COUNTA | D28: All employees
A29: Total Salary Bill | B29: =SUM(G5:G24) | C29: SUM | D29: Annual
A30: Average Salary | B30: =AVERAGE(G5:G24) | C30: AVERAGE | D30: Per employee
A31: Salary Std Dev | B31: =STDEV(G5:G24) | C31: STDEV | D31: Spread
A32: Highest Salary | B32: =MAX(G5:G24) | C32: MAX | D32: Top earner
A33: Lowest Salary | B33: =MIN(G5:G24) | C33: MIN | D33: Entry level
A34: Engineering Count | B34: =COUNTIF(E5:E24,"Engineering") | C34: COUNTIF | D34: Dept filter
A35: Avg Eng Salary | B35: =IFERROR(SUMPRODUCT((E5:E24="Engineering")*G5:G24)/COUNTIF(E5:E24,"Engineering"),0) | C35: SUMPRODUCT/COUNTIF | D35: Dept average
A36: Grade A Count | B36: =COUNTIF(J5:J24,"A") | C36: COUNTIF | D36: Grade A only
A37: Senior Employees | B37: =COUNTIF(K5:K24,"Senior") | C37: COUNTIF | D37: Status=Senior
A38: Avg Tenure (Yrs) | B38: =ROUND(AVERAGE(I5:I24),1) | C38: ROUND+AVERAGE | D38: All employees
A39: Count with Email | B39: =COUNTA(L5:L24) | C39: COUNTA | D39: Email populated
A40: Salary RANK #1 | B40: =IFERROR(INDEX(D5:D24,MATCH(1,RANK(G5:G24,G5:G24,0),0)),"N/A") | C40: INDEX+MATCH+RANK | D40: Top salary name
A41: Columns in Table | B41: =COLUMNS(A4:L4) | C41: COLUMNS | D41: Field count
A42: Count Non-Blank IDs | B42: =COUNT(IF(ISTEXT(A5:A24),1)) | C42: COUNT+IF+ISTEXT | D42: Array formula proxy

Sheet Product Lookup
A1: 🔍 Product Catalog — VLOOKUP / XLOOKUP / HLOOKUP / INDEX-MATCH
A3: PRODUCT MASTER TABLE | J3: DYNAMIC LOOKUP PANEL
A4: SKU | B4: Product Name | C4: Category | D4: Subcategory | E4: List Price | F4: Cost | G4: Margin $ | H4: Margin % | J4: Lookup Field | K4: Input | L4: Result | M4: Formula Type | N4: Notes
A5: PRD-001 | B5: Cloud Suite Pro | C5: Software | D5: SaaS | E5: 1499 | F5: 180 | G5: =E5-F5 | H5: =IFERROR(G5/E5,0) | J5: Lookup SKU ↑ | K5: PRD-008
A6: PRD-002 | B6: DataCore Analytics | C6: Software | D6: Analytics | E6: 899 | F6: 120 | G6: =E6-F6 | H6: =IFERROR(G6/E6,0) | J6: Product Name (VLOOKUP) | K6: =IFERROR(VLOOKUP($K$5,$A$5:$H$19,2,FALSE),"Not found") | L6: VLOOKUP | M6: Exact match col 2
A7: PRD-003 | B7: SecureEdge Gateway | C7: Hardware | D7: Network | E7: 2299 | F7: 890 | G7: =E7-F7 | H7: =IFERROR(G7/E7,0) | J7: Category (XLOOKUP) | K7: =IFERROR(_xludf.XLOOKUP($K$5,$A$5:$A$19,$C$5:$C$19,"Not found"),"Err") | L7: XLOOKUP | M7: Modern lookup
A8: PRD-004 | B8: MobileForce Platform | C8: Software | D8: Mobile | E8: 649 | F8: 75 | G8: =E8-F8 | H8: =IFERROR(G8/E8,0) | J8: List Price (INDEX/MATCH) | K8: =IFERROR(INDEX($E$5:$E$19,MATCH($K$5,$A$5:$A$19,0)),"N/A") | L8: INDEX+MATCH | M8: Flexible
A9: PRD-005 | B9: Apex Server X1 | C9: Hardware | D9: Compute | E9: 8499 | F9: 4200 | G9: =E9-F9 | H9: =IFERROR(G9/E9,0) | J9: Margin % (XLOOKUP) | K9: =IFERROR(_xludf.XLOOKUP($K$5,$A$5:$A$19,$H$5:$H$19,NA()),"N/A") | L9: XLOOKUP+NA | M9: Returns NA if missing
A10: PRD-006 | B10: StorageVault 10TB | C10: Hardware | D10: Storage | E10: 1199 | F10: 450 | G10: =E10-F10 | H10: =IFERROR(G10/E10,0) | J10: SKU Found? (ISNUMBER) | K10: =IF(ISNUMBER(MATCH($K$5,$A$5:$A$19,0)),"✔ Found","✘ Missing") | L10: ISNUMBER+MATCH | M10: Existence check
A11: PRD-007 | B11: API Connect Hub | C11: Software | D11: Integration | E11: 399 | F11: 40 | G11: =E11-F11 | H11: =IFERROR(G11/E11,0) | J11: Row # of SKU | K11: =IFERROR(MATCH($K$5,$A$5:$A$19,0)+4,"N/A") | L11: MATCH | M11: Absolute row
A12: PRD-008 | B12: AI Insights Engine | C12: Software | D12: AI/ML | E12: 3999 | F12: 500 | G12: =E12-F12 | H12: =IFERROR(G12/E12,0) | J12: IFNA Demo | K12: =_xludf.IFNA(VLOOKUP("ZZZZ",$A$5:$H$19,2,FALSE),"No such SKU") | L12: IFNA | M12: Returns custom on NA
A13: PRD-009 | B13: HyperSwitch 48P | C13: Hardware | D13: Network | E13: 4599 | F13: 1800 | G13: =E13-F13 | H13: =IFERROR(G13/E13,0) | J13: ISERROR Check | K13: =IF(ISERROR(VLOOKUP($K$5,$A$5:$A$19,1,FALSE)),"Error","OK") | L13: ISERROR | M13: Generic error trap
A14: PRD-010 | B14: DevOps Pipeline | C14: Software | D14: DevOps | E14: 799 | F14: 90 | G14: =E14-F14 | H14: =IFERROR(G14/E14,0) | J14: Address of Match | K14: =IFERROR(ADDRESS(MATCH($K$5,$A$5:$A$19,0)+4,1,1),"N/A") | L14: ADDRESS+MATCH | M14: Returns cell addr
A15: PRD-011 | B15: Backup Manager | C15: Software | D15: Data Mgmt | E15: 299 | F15: 35 | G15: =E15-F15 | H15: =IFERROR(G15/E15,0) | J15: HLOOKUP Avg SW Price | K15: =IFERROR(HLOOKUP("Software",B23:H26,2,FALSE),"N/A") | L15: HLOOKUP | M15: Reads horiz table
A16: PRD-012 | B16: GPU Accelerator V2 | C16: Hardware | D16: Compute | E16: 12999 | F16: 6500 | G16: =E16-F16 | H16: =IFERROR(G16/E16,0) | J16: NUMBERVALUE Demo | K16: =IFERROR(_xludf.NUMBERVALUE(TEXT(INDEX($E$5:$E$19,MATCH($K$5,$A$5:$A$19,0)),"0.00"),".",","),"N/A") | L16: NUMBERVALUE+TEXT | M16: Text→number
A17: PRD-013 | B17: Compliance Tracker | C17: Software | D17: GRC | E17: 549 | F17: 65 | G17: =E17-F17 | H17: =IFERROR(G17/E17,0) | J17: ISNA Demo | K17: =IF(ISNA(MATCH("FAKE",$A$5:$A$19,0)),"No match (ISNA=TRUE)","Found") | L17: ISNA | M17: Specific NA check
A18: PRD-014 | B18: Smart NAS 20TB | C18: Hardware | D18: Storage | E18: 2899 | F18: 1100 | G18: =E18-F18 | H18: =IFERROR(G18/E18,0)
A19: PRD-015 | B19: Identity Guard | C19: Software | D19: Security | E19: 749 | F19: 85 | G19: =E19-F19 | H19: =IFERROR(G19/E19,0) | J19: SUMPRODUCT ANALYTICS
J20: Metric | K20: Value | L20: Formula | M20: Notes
J21: Software Revenue Potential | K21: =SUMPRODUCT(($C$5:$C$19="Software")*$E$5:$E$19) | L21: SUMPRODUCT conditional
A22: CATEGORY PRICE LOOKUP TABLE (used by HLOOKUP) | J22: Hardware Revenue Potential | K22: =SUMPRODUCT(($C$5:$C$19="Hardware")*$E$5:$E$19) | L22: SUMPRODUCT conditional
A23: Metric | B23: Software | C23: Hardware | D23: Storage | E23: Network | F23: Compute | G23: AI/ML | H23: Security | J23: Weighted Avg Margin % | K23: =IFERROR(SUMPRODUCT($E$5:$E$19,$H$5:$H$19)/SUM($E$5:$E$19),0) | L23: SUMPRODUCT/SUM weighted
A24: Avg List Price | B24: =IFERROR(AVERAGEIF($C$5:$C$19,B23,$E$5:$E$19),0) | C24: =IFERROR(AVERAGEIF($C$5:$C$19,C23,$E$5:$E$19),0) | D24: =IFERROR(AVERAGEIF($C$5:$C$19,D23,$E$5:$E$19),0) | E24: =IFERROR(AVERAGEIF($C$5:$C$19,E23,$E$5:$E$19),0) | F24: =IFERROR(AVERAGEIF($C$5:$C$19,F23,$E$5:$E$19),0) | G24: =IFERROR(AVERAGEIF($C$5:$C$19,G23,$E$5:$E$19),0) | H24: =IFERROR(AVERAGEIF($C$5:$C$19,H23,$E$5:$E$19),0) | J24: Count Price > $1000 | K24: =SUMPRODUCT(($E$5:$E$19>1000)*1) | L24: SUMPRODUCT boolean
A25: Count SKUs | B25: =COUNTIF($C$5:$C$19,B23) | C25: =COUNTIF($C$5:$C$19,C23) | D25: =COUNTIF($C$5:$C$19,D23) | E25: =COUNTIF($C$5:$C$19,E23) | F25: =COUNTIF($C$5:$C$19,F23) | G25: =COUNTIF($C$5:$C$19,G23) | H25: =COUNTIF($C$5:$C$19,H23) | J25: High-margin SW count | K25: =SUMPRODUCT(($C$5:$C$19="Software")*($H$5:$H$19>0.8)) | L25: SUMPRODUCT multi-condition
A26: Avg Margin % | B26: =IFERROR(AVERAGEIF($C$5:$C$19,B23,$H$5:$H$19),0) | C26: =IFERROR(AVERAGEIF($C$5:$C$19,C23,$H$5:$H$19),0) | D26: =IFERROR(AVERAGEIF($C$5:$C$19,D23,$H$5:$H$19),0) | E26: =IFERROR(AVERAGEIF($C$5:$C$19,E23,$H$5:$H$19),0) | F26: =IFERROR(AVERAGEIF($C$5:$C$19,F23,$H$5:$H$19),0) | G26: =IFERROR(AVERAGEIF($C$5:$C$19,G23,$H$5:$H$19),0) | H26: =IFERROR(AVERAGEIF($C$5:$C$19,H23,$H$5:$H$19),0) | J26: COLUMN of Price col | K26: =COLUMN($E$5) | L26: COLUMN function
J27: LARGE 1st price | K27: =LARGE($E$5:$E$19,1) | L27: LARGE
J28: LARGE 3rd price | K28: =LARGE($E$5:$E$19,3) | L28: LARGE
J29: VALUE of text number | K29: =VALUE(TEXT(LARGE($E$5:$E$19,1),"0.00")) | L29: VALUE+TEXT+LARGE
J30: ROW-weighted sum | K30: =SUMPRODUCT((ROW($A$5:$A$19)-ROW($A$5)+1)*$G$5:$G$19) | L30: ROW inside SUMPRODUCT

Sheet Sales Tracker
A1: 🏆 Sales Performance Tracker — RANK, LARGE, COUNTIF, SUMPRODUCT
A3: QUARTERLY SALES DATA
A4: Rep ID | B4: Rep Name | C4: Region | D4: Q1 | E4: Q2 | F4: Q3 | G4: Q4 | H4: Annual Total | I4: Target | J4: % to Target | K4: Rank
A5: R01 | B5: Cassandra Blake | C5: Northeast | D5: 284000 | E5: 312000 | F5: 298000 | G5: 341000 | H5: =SUM(D5:G5) | I5: 1150000 | J5: =IFERROR(H5/I5,0) | K5: =RANK(H5,$H$5:$H$16,0)
A6: R02 | B6: Marcus Powell | C6: Southeast | D6: 198000 | E6: 221000 | F6: 245000 | G6: 267000 | H6: =SUM(D6:G6) | I6: 950000 | J6: =IFERROR(H6/I6,0) | K6: =RANK(H6,$H$5:$H$16,0)
A7: R03 | B7: Ingrid Svensson | C7: Midwest | D7: 312000 | E7: 289000 | F7: 334000 | G7: 358000 | H7: =SUM(D7:G7) | I7: 1200000 | J7: =IFERROR(H7/I7,0) | K7: =RANK(H7,$H$5:$H$16,0)
A8: R04 | B8: DeShawn Harris | C8: Southwest | D8: 167000 | E8: 189000 | F8: 201000 | G8: 224000 | H8: =SUM(D8:G8) | I8: 850000 | J8: =IFERROR(H8/I8,0) | K8: =RANK(H8,$H$5:$H$16,0)
A9: R05 | B9: Valentina Rossi | C9: West | D9: 398000 | E9: 412000 | F9: 445000 | G9: 489000 | H9: =SUM(D9:G9) | I9: 1600000 | J9: =IFERROR(H9/I9,0) | K9: =RANK(H9,$H$5:$H$16,0)
A10: R06 | B10: Jonathan Kim | C10: Northeast | D10: 275000 | E10: 291000 | F10: 308000 | G10: 322000 | H10: =SUM(D10:G10) | I10: 1100000 | J10: =IFERROR(H10/I10,0) | K10: =RANK(H10,$H$5:$H$16,0)
A11: R07 | B11: Amelia Torres | C11: Southeast | D11: 143000 | E11: 168000 | F11: 152000 | G11: 187000 | H11: =SUM(D11:G11) | I11: 700000 | J11: =IFERROR(H11/I11,0) | K11: =RANK(H11,$H$5:$H$16,0)
A12: R08 | B12: Patrick O'Connell | C12: Midwest | D12: 321000 | E12: 344000 | F12: 367000 | G12: 401000 | H12: =SUM(D12:G12) | I12: 1400000 | J12: =IFERROR(H12/I12,0) | K12: =RANK(H12,$H$5:$H$16,0)
A13: R09 | B13: Zara Mahmoud | C13: West | D13: 289000 | E13: 310000 | F13: 342000 | G13: 378000 | H13: =SUM(D13:G13) | I13: 1250000 | J13: =IFERROR(H13/I13,0) | K13: =RANK(H13,$H$5:$H$16,0)
A14: R10 | B14: Elijah Washington | C14: Southwest | D14: 212000 | E14: 235000 | F14: 258000 | G14: 281000 | H14: =SUM(D14:G14) | I14: 1000000 | J14: =IFERROR(H14/I14,0) | K14: =RANK(H14,$H$5:$H$16,0)
A15: R11 | B15: Hana Watanabe | C15: West | D15: 356000 | E15: 389000 | F15: 412000 | G15: 444000 | H15: =SUM(D15:G15) | I15: 1500000 | J15: =IFERROR(H15/I15,0) | K15: =RANK(H15,$H$5:$H$16,0)
A16: R12 | B16: Brendan O'Neill | C16: Northeast | D16: 198000 | E16: 215000 | F16: 232000 | G16: 249000 | H16: =SUM(D16:G16) | I16: 900000 | J16: =IFERROR(H16/I16,0) | K16: =RANK(H16,$H$5:$H$16,0)
A17: TOTALS | D17: =SUM(D5:D16) | E17: =SUM(E5:E16) | F17: =SUM(F5:F16) | G17: =SUM(G5:G16) | H17: =SUM(H5:H16) | I17: =SUM(I5:I16) | J17: =IFERROR(H17/I17,0)
A19: SALES ANALYTICS
A20: Metric | B20: Value | C20: Formula | D20: Period | E20: Notes
A21: Top Rep (by Annual) | B21: =IFERROR(INDEX(B5:B16,MATCH(MAX(H5:H16),H5:H16,0)),"N/A") | C21: INDEX+MATCH+MAX | D21: Full year
A22: Highest Single Quarter | B22: =MAX(D5:G16) | C22: MAX | D22: All quarters
A23: Lowest Annual Total | B23: =MIN(H5:H16) | C23: MIN | D23: Full year
A24: Reps >100% Target | B24: =COUNTIF(J5:J16,">1") | C24: COUNTIF | D24: All reps
A25: Reps <80% Target | B25: =COUNTIF(J5:J16,"<0.8") | C25: COUNTIF | D25: At-risk
A26: Avg Q4 Performance | B26: =AVERAGE(G5:G16) | C26: AVERAGE | D26: Q4 only
A27: Std Dev Annual Sales | B27: =STDEV(H5:H16) | C27: STDEV | D27: Dispersion
A28: Total West Region | B28: =SUMPRODUCT((C5:C16="West")*H5:H16) | C28: SUMPRODUCT | D28: Region filter
A29: 2nd Highest Annual | B29: =LARGE(H5:H16,2) | C29: LARGE | D29: Runner-up
A30: 3rd Highest Annual | B30: =LARGE(H5:H16,3) | C30: LARGE | D30: 3rd place
A31: OFFSET: Q3 of Rank 1 | B31: =IFERROR(OFFSET(D5,MATCH(1,K5:K16,0)-1,2),0) | C31: OFFSET+MATCH | D31: Dynamic range
A32: Northeast Rep Count | B32: =COUNTIF(C5:C16,"Northeast") | C32: COUNTIF | D32: Region
A33: CHOOSE Quarter Label | B33: =CHOOSE(2,"Q1 2024","Q2 2024","Q3 2024","Q4 2024") | C33: CHOOSE | D33: Selector demo
A34: COLUMN of Q1 column | B34: =COLUMN(D5) | C34: COLUMN | D34: Column index

Sheet Statistical Analysis
A1: 📈 Statistical Analysis — NORMDIST, STDEV, AVERAGE, OFFSET, ROW
A3: 24-MONTH REVENUE ACTUALS ($M) | H3: DESCRIPTIVE STATISTICS
A4: Period | B4: Month | C4: Year | D4: Revenue ($M) | E4: MoM Growth | F4: 3-Mo Avg (OFFSET) | H4: Statistic | I4: Value | J4: Formula | K4: Notes
A5: =ROW()-ROW($A$5)+1 | B5: Jan | C5: 2023 | D5: 5.8 | E5: =NA() | F5: =NA() | H5: Count | I5: =COUNT(D5:D28) | J5: COUNT | K5: All months
A6: =ROW()-ROW($A$5)+1 | B6: Feb | C6: 2023 | D6: 6.1 | E6: =IFERROR((D6-D5)/D5,NA()) | F6: =NA() | H6: Mean ($M) | I6: =AVERAGE(D5:D28) | J6: AVERAGE | K6: Arithmetic mean
A7: =ROW()-ROW($A$5)+1 | B7: Mar | C7: 2023 | D7: 6.4 | E7: =IFERROR((D7-D6)/D6,NA()) | F7: =IFERROR(AVERAGE(OFFSET(D7,-2,0,3,1)),NA()) | H7: Std Dev ($M) | I7: =STDEV(D5:D28) | J7: STDEV | K7: Sample std dev
A8: =ROW()-ROW($A$5)+1 | B8: Apr | C8: 2023 | D8: 6.9 | E8: =IFERROR((D8-D7)/D7,NA()) | F8: =IFERROR(AVERAGE(OFFSET(D8,-2,0,3,1)),NA()) | H8: Min ($M) | I8: =MIN(D5:D28) | J8: MIN | K8: Lowest month
A9: =ROW()-ROW($A$5)+1 | B9: May | C9: 2023 | D9: 7.2 | E9: =IFERROR((D9-D8)/D8,NA()) | F9: =IFERROR(AVERAGE(OFFSET(D9,-2,0,3,1)),NA()) | H9: Max ($M) | I9: =MAX(D5:D28) | J9: MAX | K9: Peak month
A10: =ROW()-ROW($A$5)+1 | B10: Jun | C10: 2023 | D10: 7.8 | E10: =IFERROR((D10-D9)/D9,NA()) | F10: =IFERROR(AVERAGE(OFFSET(D10,-2,0,3,1)),NA()) | H10: Range ($M) | I10: =MAX(D5:D28)-MIN(D5:D28) | J10: MAX-MIN | K10: Spread
A11: =ROW()-ROW($A$5)+1 | B11: Jul | C11: 2023 | D11: 7.5 | E11: =IFERROR((D11-D10)/D10,NA()) | F11: =IFERROR(AVERAGE(OFFSET(D11,-2,0,3,1)),NA()) | H11: Median est. | I11: =IFERROR((LARGE(D5:D28,12)+LARGE(D5:D28,13))/2,0) | J11: LARGE | K11: Approx median
A12: =ROW()-ROW($A$5)+1 | B12: Aug | C12: 2023 | D12: 8.1 | E12: =IFERROR((D12-D11)/D11,NA()) | F12: =IFERROR(AVERAGE(OFFSET(D12,-2,0,3,1)),NA()) | H12: CoV | I12: =IFERROR(STDEV(D5:D28)/AVERAGE(D5:D28),0) | J12: STDEV/AVERAGE | K12: Coeff of variation
A13: =ROW()-ROW($A$5)+1 | B13: Sep | C13: 2023 | D13: 8.6 | E13: =IFERROR((D13-D12)/D12,NA()) | F13: =IFERROR(AVERAGE(OFFSET(D13,-2,0,3,1)),NA()) | H13: Q4 2024 OFFSET | I13: =IFERROR(AVERAGE(OFFSET(D28,-2,0,3,1)),0) | J13: OFFSET | K13: Last 3 months
A14: =ROW()-ROW($A$5)+1 | B14: Oct | C14: 2023 | D14: 9 | E14: =IFERROR((D14-D13)/D13,NA()) | F14: =IFERROR(AVERAGE(OFFSET(D14,-2,0,3,1)),NA()) | H14: H2 2024 OFFSET | I14: =IFERROR(SUM(OFFSET(D28,-5,0,6,1)),0) | J14: OFFSET | K14: Last 6 months
A15: =ROW()-ROW($A$5)+1 | B15: Nov | C15: 2023 | D15: 9.4 | E15: =IFERROR((D15-D14)/D14,NA()) | F15: =IFERROR(AVERAGE(OFFSET(D15,-2,0,3,1)),NA()) | H15: COLUMNS check | I15: =COLUMNS(A4:F4) | J15: COLUMNS | K15: Fields in table
A16: =ROW()-ROW($A$5)+1 | B16: Dec | C16: 2023 | D16: 9.9 | E16: =IFERROR((D16-D15)/D15,NA()) | F16: =IFERROR(AVERAGE(OFFSET(D16,-2,0,3,1)),NA())
A17: =ROW()-ROW($A$5)+1 | B17: Jan | C17: 2024 | D17: 10.2 | E17: =IFERROR((D17-D16)/D16,NA()) | F17: =IFERROR(AVERAGE(OFFSET(D17,-2,0,3,1)),NA()) | H17: NORMAL DISTRIBUTION TABLE
A18: =ROW()-ROW($A$5)+1 | B18: Feb | C18: 2024 | D18: 10.8 | E18: =IFERROR((D18-D17)/D17,NA()) | F18: =IFERROR(AVERAGE(OFFSET(D18,-2,0,3,1)),NA()) | H18: Month | I18: Revenue | J18: Z-Score | K18: CDF (NORMDIST) | L18: Above/Below Mean | M18: Probability Band
A19: =ROW()-ROW($A$5)+1 | B19: Mar | C19: 2024 | D19: 11.3 | E19: =IFERROR((D19-D18)/D18,NA()) | F19: =IFERROR(AVERAGE(OFFSET(D19,-2,0,3,1)),NA()) | H19: =B5&" "&C5 | I19: =D5 | J19: =IFERROR((I19-AVERAGE($D$5:$D$28))/STDEV($D$5:$D$28),0) | K19: =IFERROR(NORMDIST(I19,AVERAGE($D$5:$D$28),STDEV($D$5:$D$28),TRUE),0) | L19: =IF(J19>0,"Above","Below") | M19: =IF(ABS(J19)<=1,"Within 1σ",IF(ABS(J19)<=2,"Within 2σ","Outlier >2σ"))
A20: =ROW()-ROW($A$5)+1 | B20: Apr | C20: 2024 | D20: 11.9 | E20: =IFERROR((D20-D19)/D19,NA()) | F20: =IFERROR(AVERAGE(OFFSET(D20,-2,0,3,1)),NA()) | H20: =B6&" "&C6 | I20: =D6 | J20: =IFERROR((I20-AVERAGE($D$5:$D$28))/STDEV($D$5:$D$28),0) | K20: =IFERROR(NORMDIST(I20,AVERAGE($D$5:$D$28),STDEV($D$5:$D$28),TRUE),0) | L20: =IF(J20>0,"Above","Below") | M20: =IF(ABS(J20)<=1,"Within 1σ",IF(ABS(J20)<=2,"Within 2σ","Outlier >2σ"))
A21: =ROW()-ROW($A$5)+1 | B21: May | C21: 2024 | D21: 12.4 | E21: =IFERROR((D21-D20)/D20,NA()) | F21: =IFERROR(AVERAGE(OFFSET(D21,-2,0,3,1)),NA()) | H21: =B7&" "&C7 | I21: =D7 | J21: =IFERROR((I21-AVERAGE($D$5:$D$28))/STDEV($D$5:$D$28),0) | K21: =IFERROR(NORMDIST(I21,AVERAGE($D$5:$D$28),STDEV($D$5:$D$28),TRUE),0) | L21: =IF(J21>0,"Above","Below") | M21: =IF(ABS(J21)<=1,"Within 1σ",IF(ABS(J21)<=2,"Within 2σ","Outlier >2σ"))
A22: =ROW()-ROW($A$5)+1 | B22: Jun | C22: 2024 | D22: 13 | E22: =IFERROR((D22-D21)/D21,NA()) | F22: =IFERROR(AVERAGE(OFFSET(D22,-2,0,3,1)),NA()) | H22: =B8&" "&C8 | I22: =D8 | J22: =IFERROR((I22-AVERAGE($D$5:$D$28))/STDEV($D$5:$D$28),0) | K22: =IFERROR(NORMDIST(I22,AVERAGE($D$5:$D$28),STDEV($D$5:$D$28),TRUE),0) | L22: =IF(J22>0,"Above","Below") | M22: =IF(ABS(J22)<=1,"Within 1σ",IF(ABS(J22)<=2,"Within 2σ","Outlier >2σ"))
A23: =ROW()-ROW($A$5)+1 | B23: Jul | C23: 2024 | D23: 12.7 | E23: =IFERROR((D23-D22)/D22,NA()) | F23: =IFERROR(AVERAGE(OFFSET(D23,-2,0,3,1)),NA()) | H23: =B9&" "&C9 | I23: =D9 | J23: =IFERROR((I23-AVERAGE($D$5:$D$28))/STDEV($D$5:$D$28),0) | K23: =IFERROR(NORMDIST(I23,AVERAGE($D$5:$D$28),STDEV($D$5:$D$28),TRUE),0) | L23: =IF(J23>0,"Above","Below") | M23: =IF(ABS(J23)<=1,"Within 1σ",IF(ABS(J23)<=2,"Within 2σ","Outlier >2σ"))
A24: =ROW()-ROW($A$5)+1 | B24: Aug | C24: 2024 | D24: 13.5 | E24: =IFERROR((D24-D23)/D23,NA()) | F24: =IFERROR(AVERAGE(OFFSET(D24,-2,0,3,1)),NA()) | H24: =B10&" "&C10 | I24: =D10 | J24: =IFERROR((I24-AVERAGE($D$5:$D$28))/STDEV($D$5:$D$28),0) | K24: =IFERROR(NORMDIST(I24,AVERAGE($D$5:$D$28),STDEV($D$5:$D$28),TRUE),0) | L24: =IF(J24>0,"Above","Below") | M24: =IF(ABS(J24)<=1,"Within 1σ",IF(ABS(J24)<=2,"Within 2σ","Outlier >2σ"))
A25: =ROW()-ROW($A$5)+1 | B25: Sep | C25: 2024 | D25: 14.1 | E25: =IFERROR((D25-D24)/D24,NA()) | F25: =IFERROR(AVERAGE(OFFSET(D25,-2,0,3,1)),NA()) | H25: =B11&" "&C11 | I25: =D11 | J25: =IFERROR((I25-AVERAGE($D$5:$D$28))/STDEV($D$5:$D$28),0) | K25: =IFERROR(NORMDIST(I25,AVERAGE($D$5:$D$28),STDEV($D$5:$D$28),TRUE),0) | L25: =IF(J25>0,"Above","Below") | M25: =IF(ABS(J25)<=1,"Within 1σ",IF(ABS(J25)<=2,"Within 2σ","Outlier >2σ"))
A26: =ROW()-ROW($A$5)+1 | B26: Oct | C26: 2024 | D26: 14.8 | E26: =IFERROR((D26-D25)/D25,NA()) | F26: =IFERROR(AVERAGE(OFFSET(D26,-2,0,3,1)),NA()) | H26: =B12&" "&C12 | I26: =D12 | J26: =IFERROR((I26-AVERAGE($D$5:$D$28))/STDEV($D$5:$D$28),0) | K26: =IFERROR(NORMDIST(I26,AVERAGE($D$5:$D$28),STDEV($D$5:$D$28),TRUE),0) | L26: =IF(J26>0,"Above","Below") | M26: =IF(ABS(J26)<=1,"Within 1σ",IF(ABS(J26)<=2,"Within 2σ","Outlier >2σ"))
A27: =ROW()-ROW($A$5)+1 | B27: Nov | C27: 2024 | D27: 15.6 | E27: =IFERROR((D27-D26)/D26,NA()) | F27: =IFERROR(AVERAGE(OFFSET(D27,-2,0,3,1)),NA()) | H27: =B13&" "&C13 | I27: =D13 | J27: =IFERROR((I27-AVERAGE($D$5:$D$28))/STDEV($D$5:$D$28),0) | K27: =IFERROR(NORMDIST(I27,AVERAGE($D$5:$D$28),STDEV($D$5:$D$28),TRUE),0) | L27: =IF(J27>0,"Above","Below") | M27: =IF(ABS(J27)<=1,"Within 1σ",IF(ABS(J27)<=2,"Within 2σ","Outlier >2σ"))
A28: =ROW()-ROW($A$5)+1 | B28: Dec | C28: 2024 | D28: 16.2 | E28: =IFERROR((D28-D27)/D27,NA()) | F28: =IFERROR(AVERAGE(OFFSET(D28,-2,0,3,1)),NA()) | H28: =B14&" "&C14 | I28: =D14 | J28: =IFERROR((I28-AVERAGE($D$5:$D$28))/STDEV($D$5:$D$28),0) | K28: =IFERROR(NORMDIST(I28,AVERAGE($D$5:$D$28),STDEV($D$5:$D$28),TRUE),0) | L28: =IF(J28>0,"Above","Below") | M28: =IF(ABS(J28)<=1,"Within 1σ",IF(ABS(J28)<=2,"Within 2σ","Outlier >2σ"))
H29: =B15&" "&C15 | I29: =D15 | J29: =IFERROR((I29-AVERAGE($D$5:$D$28))/STDEV($D$5:$D$28),0) | K29: =IFERROR(NORMDIST(I29,AVERAGE($D$5:$D$28),STDEV($D$5:$D$28),TRUE),0) | L29: =IF(J29>0,"Above","Below") | M29: =IF(ABS(J29)<=1,"Within 1σ",IF(ABS(J29)<=2,"Within 2σ","Outlier >2σ"))
H30: =B16&" "&C16 | I30: =D16 | J30: =IFERROR((I30-AVERAGE($D$5:$D$28))/STDEV($D$5:$D$28),0) | K30: =IFERROR(NORMDIST(I30,AVERAGE($D$5:$D$28),STDEV($D$5:$D$28),TRUE),0) | L30: =IF(J30>0,"Above","Below") | M30: =IF(ABS(J30)<=1,"Within 1σ",IF(ABS(J30)<=2,"Within 2σ","Outlier >2σ"))
H31: =B17&" "&C17 | I31: =D17 | J31: =IFERROR((I31-AVERAGE($D$5:$D$28))/STDEV($D$5:$D$28),0) | K31: =IFERROR(NORMDIST(I31,AVERAGE($D$5:$D$28),STDEV($D$5:$D$28),TRUE),0) | L31: =IF(J31>0,"Above","Below") | M31: =IF(ABS(J31)<=1,"Within 1σ",IF(ABS(J31)<=2,"Within 2σ","Outlier >2σ"))
H32: =B18&" "&C18 | I32: =D18 | J32: =IFERROR((I32-AVERAGE($D$5:$D$28))/STDEV($D$5:$D$28),0) | K32: =IFERROR(NORMDIST(I32,AVERAGE($D$5:$D$28),STDEV($D$5:$D$28),TRUE),0) | L32: =IF(J32>0,"Above","Below") | M32: =IF(ABS(J32)<=1,"Within 1σ",IF(ABS(J32)<=2,"Within 2σ","Outlier >2σ"))
H33: =B19&" "&C19 | I33: =D19 | J33: =IFERROR((I33-AVERAGE($D$5:$D$28))/STDEV($D$5:$D$28),0) | K33: =IFERROR(NORMDIST(I33,AVERAGE($D$5:$D$28),STDEV($D$5:$D$28),TRUE),0) | L33: =IF(J33>0,"Above","Below") | M33: =IF(ABS(J33)<=1,"Within 1σ",IF(ABS(J33)<=2,"Within 2σ","Outlier >2σ"))
H34: =B20&" "&C20 | I34: =D20 | J34: =IFERROR((I34-AVERAGE($D$5:$D$28))/STDEV($D$5:$D$28),0) | K34: =IFERROR(NORMDIST(I34,AVERAGE($D$5:$D$28),STDEV($D$5:$D$28),TRUE),0) | L34: =IF(J34>0,"Above","Below") | M34: =IF(ABS(J34)<=1,"Within 1σ",IF(ABS(J34)<=2,"Within 2σ","Outlier >2σ"))
H35: =B21&" "&C21 | I35: =D21 | J35: =IFERROR((I35-AVERAGE($D$5:$D$28))/STDEV($D$5:$D$28),0) | K35: =IFERROR(NORMDIST(I35,AVERAGE($D$5:$D$28),STDEV($D$5:$D$28),TRUE),0) | L35: =IF(J35>0,"Above","Below") | M35: =IF(ABS(J35)<=1,"Within 1σ",IF(ABS(J35)<=2,"Within 2σ","Outlier >2σ"))
H36: =B22&" "&C22 | I36: =D22 | J36: =IFERROR((I36-AVERAGE($D$5:$D$28))/STDEV($D$5:$D$28),0) | K36: =IFERROR(NORMDIST(I36,AVERAGE($D$5:$D$28),STDEV($D$5:$D$28),TRUE),0) | L36: =IF(J36>0,"Above","Below") | M36: =IF(ABS(J36)<=1,"Within 1σ",IF(ABS(J36)<=2,"Within 2σ","Outlier >2σ"))
H37: =B23&" "&C23 | I37: =D23 | J37: =IFERROR((I37-AVERAGE($D$5:$D$28))/STDEV($D$5:$D$28),0) | K37: =IFERROR(NORMDIST(I37,AVERAGE($D$5:$D$28),STDEV($D$5:$D$28),TRUE),0) | L37: =IF(J37>0,"Above","Below") | M37: =IF(ABS(J37)<=1,"Within 1σ",IF(ABS(J37)<=2,"Within 2σ","Outlier >2σ"))
H38: =B24&" "&C24 | I38: =D24 | J38: =IFERROR((I38-AVERAGE($D$5:$D$28))/STDEV($D$5:$D$28),0) | K38: =IFERROR(NORMDIST(I38,AVERAGE($D$5:$D$28),STDEV($D$5:$D$28),TRUE),0) | L38: =IF(J38>0,"Above","Below") | M38: =IF(ABS(J38)<=1,"Within 1σ",IF(ABS(J38)<=2,"Within 2σ","Outlier >2σ"))
H39: =B25&" "&C25 | I39: =D25 | J39: =IFERROR((I39-AVERAGE($D$5:$D$28))/STDEV($D$5:$D$28),0) | K39: =IFERROR(NORMDIST(I39,AVERAGE($D$5:$D$28),STDEV($D$5:$D$28),TRUE),0) | L39: =IF(J39>0,"Above","Below") | M39: =IF(ABS(J39)<=1,"Within 1σ",IF(ABS(J39)<=2,"Within 2σ","Outlier >2σ"))
H40: =B26&" "&C26 | I40: =D26 | J40: =IFERROR((I40-AVERAGE($D$5:$D$28))/STDEV($D$5:$D$28),0) | K40: =IFERROR(NORMDIST(I40,AVERAGE($D$5:$D$28),STDEV($D$5:$D$28),TRUE),0) | L40: =IF(J40>0,"Above","Below") | M40: =IF(ABS(J40)<=1,"Within 1σ",IF(ABS(J40)<=2,"Within 2σ","Outlier >2σ"))
... H42: =B28&" "&C28 | I42: =D28 | J42: =IFERROR((I42-AVERAGE($D$5:$D$28))/STDEV($D$5:$D$28),0) | K42: =IFERROR(NORMDIST(I42,AVERAGE($D$5:$D$28),STDEV($D$5:$D$28),TRUE),0) | L42: =IF(J42>0,"Above","Below") | M42: =IF(ABS(J42)<=1,"Within 1σ",IF(ABS(J42)<=2,"Within 2σ","Outlier >2σ"))

Sheet DCF Valuation
A1: 💰 DCF Valuation — NPV, IF, AND, OR, TEXT, ROUND, IFERROR
A3: FREE CASH FLOW PROJECTIONS ($M)
A4: Line Item | B4: 2025 | C4: 2026 | D4: 2027 | E4: 2028 | F4: 2029 | G4: 2030
B5: ='Revenue Model'!B8 | C5: ='Revenue Model'!C8 | D5: ='Revenue Model'!D8 | E5: ='Revenue Model'!E8 | F5: ='Revenue Model'!F8 | G5: ='Revenue Model'!G8
B6: ='Revenue Model'!B13 | C6: ='Revenue Model'!C13 | D6: ='Revenue Model'!D13 | E6: ='Revenue Model'!E13 | F6: ='Revenue Model'!F13 | G6: ='Revenue Model'!G13
B7: ='Revenue Model'!B15 | C7: ='Revenue Model'!C15 | D7: ='Revenue Model'!D15 | E7: ='Revenue Model'!E15 | F7: ='Revenue Model'!F15 | G7: ='Revenue Model'!G15
B8: ='Revenue Model'!B16 | C8: ='Revenue Model'!C16 | D8: ='Revenue Model'!D16 | E8: ='Revenue Model'!E16 | F8: ='Revenue Model'!F16 | G8: ='Revenue Model'!G16
B9: ='Revenue Model'!B18 | C9: ='Revenue Model'!C18 | D9: ='Revenue Model'!D18 | E9: ='Revenue Model'!E18 | F9: ='Revenue Model'!F18 | G9: ='Revenue Model'!G18
B10: =B8-B9 | C10: =C8-C9 | D10: =D8-D9 | E10: =E8-E9 | F10: =F8-F9 | G10: =G8-G9
B11: =B7 | C11: =C7 | D11: =D7 | E11: =E7 | F11: =F7 | G11: =G7
B12: =-ROUND(B5*Assumptions!$B$23,2) | C12: =-ROUND(C5*Assumptions!$B$23,2) | D12: =-ROUND(D5*Assumptions!$B$23,2) | E12: =-ROUND(E5*Assumptions!$B$23,2) | F12: =-ROUND(F5*Assumptions!$B$23,2) | G12: =-ROUND(G5*Assumptions!$B$23,2)
B13: -2.56 | C13: =ROUND(-C5*0.03,2) | D13: =ROUND(-D5*0.03,2) | E13: =ROUND(-E5*0.03,2) | F13: =ROUND(-F5*0.03,2) | G13: =ROUND(-G5*0.03,2)
A14: Free Cash Flow | B14: =ROUND(B10+B11+B12+B13,2) | C14: =ROUND(C10+C11+C12+C13,2) | D14: =ROUND(D10+D11+D12+D13,2) | E14: =ROUND(E10+E11+E12+E13,2) | F14: =ROUND(F10+F11+F12+F13,2) | G14: =ROUND(G10+G11+G12+G13,2)
A16: DISCOUNT FACTORS & PV CALCULATIONS
A17: Discount Rate (WACC) | B17: =Assumptions!B19
A18: Year Index | B18: 1 | C18: 2 | D18: 3 | E18: 4 | F18: 5 | G18: 6
A19: Discount Factor | B19: =IFERROR(1/(1+$B$17)^1,0) | C19: =IFERROR(1/(1+$B$17)^2,0) | D19: =IFERROR(1/(1+$B$17)^3,0) | E19: =IFERROR(1/(1+$B$17)^4,0) | F19: =IFERROR(1/(1+$B$17)^5,0) | G19: =IFERROR(1/(1+$B$17)^6,0)
A20: PV of FCF ($M) | B20: =ROUND(B14*B19,2) | C20: =ROUND(C14*C19,2) | D20: =ROUND(D14*D19,2) | E20: =ROUND(E14*E19,2) | F20: =ROUND(F14*F19,2) | G20: =ROUND(G14*G19,2)
A22: VALUATION SUMMARY
A23: Metric | B23: Value | C23: Formula | D23: Notes | E23: Verdict
A24: Sum PV of FCFs | B24: → see E column | C24: SUM | D24: 5-yr PVs | E24: =SUM(B20:G20)
A25: NPV (Excel function) | B25: → see E column | C25: NPV | D25: Excel NPV fn | E25: =IFERROR(NPV(B17,C14:G14)+B14,0)
A26: Terminal Value | B26: → see E column | C26: Gordon Growth | D26: Perpetuity | E26: =IFERROR(G14*(1+Assumptions!B20)/(B17-Assumptions!B20),0)
A27: PV of Terminal Value | B27: → see E column | C27: Math | D27: Discounted TV | E27: =IFERROR(E26/(1+B17)^6,0)
A28: Enterprise Value | B28: → see E column | C28: Sum | D28: EV = PV FCF + PV TV | E28: =IFERROR(E24+E27,0)
A29: EV/Revenue Multiple | B29: → see E column | C29: Division | D29: Turn of revenue | E29: =IFERROR(E28/B5,0)
A30: NPV Signal | B30: → see E column | C30: IF+AND | D30: Buy/Hold/Sell | E30: =IF(AND(E28>0,E24>0),IF(E28>E24*1.5,"Strong Buy",IF(E28>E24,"Buy","Hold")),"Review")
A31: EV as TEXT | B31: → see E column | C31: TEXT | D31: Formatted string | E31: =TEXT(E28,"$#,##0.0")&"M"
A32: OR: distressed? | B32: → see E column | C32: OR | D32: Sanity check | E32: =IF(OR(E28<0,B17>0.15),"⚠ Review assumptions","✔ Parameters OK")
A33: ROUND EV to $10M | B33: → see E column | C33: ROUND | D33: Rounded EV | E33: =IFERROR(ROUND(E28/10,0)*10,0)
A34: ROUNDDOWN FCF Yr1 | B34: → see E column | C34: ROUNDDOWN | D34: Floor of FCF | E34: =ROUNDDOWN(B14,0)
A35: MID of NPV Signal | B35: → see E column | C35: MID | D35: First 4 chars | E35: =IFERROR(MID(E30,1,4),"N/A")
A36: RIGHT of EV text | B36: → see E column | C36: RIGHT | D36: Last character | E36: =RIGHT(E31,1)

Sheet Formula Toolkit
A1: 🧰 Formula Toolkit — Text, Address, Column, Row, String Functions
A3: STRING FUNCTION DEMONSTRATIONS
A4: Function(s) | B4: Input | C4: Formula | D4: Result | E4: Category | F4: Notes
A5: LEFT | B5: Apex Dynamics Inc | C5: LEFT("Apex Dynamics Inc",4) | D5: =LEFT("Apex Dynamics Inc",4) | E5: Text | F5: First 4 chars
A6: RIGHT | B6: FY2024-Q3 | C6: RIGHT("FY2024-Q3",2) | D6: =RIGHT("FY2024-Q3",2) | E6: Text | F6: Last 2 chars
A7: MID | B7: PRD-008-EMEA | C7: MID("PRD-008-EMEA",5,3) | D7: =MID("PRD-008-EMEA",5,3) | E7: Text | F7: Chars 5-7
A8: CONCATENATE | B8: First + Last | C8: CONCATENATE("Apex"," ","Dynamics") | D8: =CONCATENATE("Apex"," ","Dynamics") | E8: Text | F8: Join strings
A9: TEXT (date) | B9: Today's date | C9: TEXT(TODAY(),"MMMM DD, YYYY") | D9: =TEXT(TODAY(),"MMMM DD, YYYY") | E9: Text | F9: Format date
A10: TEXT (number) | B10: $1234567.89 | C10: TEXT(1234567.89,"$#,##0.00") | D10: =TEXT(1234567.89,"$#,##0.00") | E10: Text | F10: Format number
A11: VALUE | B11: "1,234.56" | C11: VALUE("1234.56") | D11: =VALUE("1234.56") | E11: Text | F11: String to number
A12: NUMBERVALUE | B12: "1.234,56" EU | C12: NUMBERVALUE("1234.56",".",",") | D12: =_xludf.NUMBERVALUE("1234.56",".",",") | E12: Text | F12: Locale-aware
A13: ISTEXT | B13: Check "hello" | C13: ISTEXT("hello") | D13: =ISTEXT("hello") | E13: Info | F13: TRUE if text
A14: ISTEXT (num) | B14: Check 42 | C14: ISTEXT(42) | D14: =ISTEXT(42) | E14: Info | F14: FALSE for number
A15: ISNUMBER | B15: Check 3.14 | C15: ISNUMBER(3.14) | D15: =ISNUMBER(3.14) | E15: Info | F15: TRUE if numeric
A16: ISBLANK | B16: Empty cell | C16: ISBLANK("") | D16: =ISBLANK("") | E16: Info | F16: TRUE if blank
A17: ISERROR | B17: 1/0 | C17: ISERROR(1/0) | D17: =ISERROR(1/0) | E17: Info | F17: TRUE on error
A18: ISNA | B18: NA() | C18: ISNA(NA()) | D18: =ISNA(NA()) | E18: Info | F18: Specific NA check
A19: ADDRESS | B19: Row 5, Col 3 | C19: ADDRESS(5,3,1) | D19: =ADDRESS(5,3,1) | E19: Ref | F19: Absolute address
A20: ADDRESS (rel) | B20: Row 10, Col 2 | C20: ADDRESS(10,2,4) | D20: =ADDRESS(10,2,4) | E20: Ref | F20: Relative address
A21: COLUMN | B21: Cell E1 | C21: COLUMN($E$1) | D21: =COLUMN($E$1) | E21: Ref | F21: Returns 5
A22: ROW | B22: Cell A10 | C22: ROW($A$10) | D22: =ROW($A$10) | E22: Ref | F22: Returns 10
A23: COLUMNS | B23: Range A1:H1 | C23: COLUMNS($A$1:$H$1) | D23: =COLUMNS($A$1:$H$1) | E23: Ref | F23: Returns 8
A24: COUNTA | B24: Non-blank count | C24: COUNTA($A$5:$A$18) | D24: =COUNTA($A$5:$A$18) | E24: Stats | F24: Count non-empty
A25: COUNT | B25: Numeric count | C25: COUNT($A$5:$A$18) | D25: =COUNT($A$5:$A$18) | E25: Stats | F25: Count numbers
A26: LEFT+VALUE | B26: Extract digits | C26: VALUE(LEFT("Q3-2024",2)) | D26: =VALUE(LEFT("Q3-2024",2)) | E26: Combo | F26: Extract then parse
A27: MID+VALUE | B27: Year from code | C27: VALUE(MID("FY2024-Q3",3,4)) | D27: =VALUE(MID("FY2024-Q3",3,4)) | E27: Combo | F27: Year from string
A28: IFERROR+VALUE | B28: Safe parse | C28: IFERROR(VALUE("abc"),0) | D28: =IFERROR(VALUE("abc"),0) | E28: Combo | F28: Error-safe parse
A29: CONCATENATE+TEXT | B29: Build label | C29: CONCATENATE("FY",TEXT(2024,"0"),"-Q",TEXT(3,"0")) | D29: =CONCATENATE("FY",TEXT(2024,"0"),"-Q",TEXT(3,"0")) | E29: Combo | F29: Formatted label
A30: IFNA demo | B30: Safe XLOOKUP | C30: IFNA(VLOOKUP("FAKE",A5:A18,1,FALSE),"Not found") | D30: =_xludf.IFNA(VLOOKUP("FAKE",A5:A18,1,FALSE),"Not found") | E30: Combo | F30: IFNAs NA
A31: CHOOSE+TEXT | B31: Quarter names | C31: TEXT(CHOOSE(2,1,2,3,4),""Q"0") | D31: =TEXT(CHOOSE(2,1,2,3,4),""Q"0") | E31: Combo | F31: Format selected
A32: ADDRESS+MATCH | B32: Dynamic address | C32: ADDRESS(MATCH("E001",Employee_Directory!$A$5:$A$24,0)+4,7) | D32: =ADDRESS(MATCH("E001",Employee_Directory!$A$5:$A$24,0)+4,7) | E32: Combo | F32: Employee salary cell
A33: ROW array sum | B33: Weighted index | C33: SUMPRODUCT((ROW($A$5:$A$24)-ROW($A$5)+1)*1) | D33: =SUMPRODUCT((ROW($A$5:$A$24)-ROW($A$5)+1)*1) | E33: Combo | F33: 1+2+...+20
A34: OFFSET+AVERAGE | B34: Rolling 3-mo avg | C34: IFERROR(AVERAGE(OFFSET(Statistical_Analysis!$D$28,-2,0,3,1)),0) | D34: =IFERROR(AVERAGE(OFFSET(Statistical_Analysis!$D$28,-2,0,3,1)),0) | E34: Combo | F34: Last 3 months

Sheet Function Index
A1: 📚 Complete Function Index — All 45 Functions in This Workbook
A3: FUNCTION REFERENCE GUIDE
A4: Function | B4: Category | C4: Sheet(s) | D4: Purpose | E4: Syntax Pattern | F4: Notes
A5: IF | B5: Logical | C5: All | D5: Conditional result | E5: IF(test,true,false) | F5: Core branching
A6: IFERROR | B6: Logical | C6: All | D6: Suppress any error | E6: IFERROR(expr,fallback) | F6: Catch-all
A7: IFNA | B7: Logical | C7: Product Lookup, Toolkit | D7: Suppress only NA | E7: IFNA(expr,fallback) | F7: Specific NA
A8: ISBLANK | B8: Info | C8: Assumptions | D8: Check empty cell | E8: ISBLANK(cell) | F8: Returns TRUE/FALSE
A9: ISNUMBER | B9: Info | C9: Product Lookup, Toolkit | D9: Check numeric | E9: ISNUMBER(value) | F9: Returns TRUE/FALSE
A10: ISTEXT | B10: Info | C10: Assumptions, Toolkit | D10: Check text type | E10: ISTEXT(value) | F10: Returns TRUE/FALSE
A11: ISERROR | B11: Info | C11: Product Lookup, Toolkit | D11: Check any error | E11: ISERROR(value) | F11: Returns TRUE/FALSE
A12: ISNA | B12: Info | C12: Product Lookup, Toolkit | D12: Check NA error | E12: ISNA(value) | F12: Specific
A13: AND | B13: Logical | C13: Assumptions, DCF | D13: All conditions true | E13: AND(cond1,cond2,...) | F13: Logical gate
A14: OR | B14: Logical | C14: Assumptions, DCF | D14: Any condition true | E14: OR(cond1,cond2,...) | F14: Logical gate
A15: CHOOSE | B15: Lookup | C15: Assumptions, Sales | D15: Pick nth item | E15: CHOOSE(n,v1,v2,...) | F15: Scenario select
... A48: NUMBERVALUE | B48: Text | C48: Product Lookup, Toolkit | D48: Locale-aware parse | E48: NUMBERVALUE(t,dec,grp) | F48: EU decimals
