Workbook

Sheet Assumptions
A1: 📋 Model Assumptions — Edit Blue Cells
A3: REVENUE ASSUMPTIONS
A4: Parameter | B4: Value | C4: Unit | D4: Notes
A5: Base Revenue (Year 1) | B5: 5000000 | C5: $ | D5: Starting revenue
A6: Annual Growth Rate | B6: 0.08 | C6: % | D6: YoY growth assumption
A7: Gross Margin | B7: 0.62 | C7: % | D7: % of revenue
A8: OpEx % Revenue | B8: 0.35 | C8: % | D8: Operating expenses
A9: Tax Rate | B9: 0.21 | C9: % | D9: Effective tax rate
A10: Discount Rate | B10: 0.1 | C10: % | D10: WACC for NPV
A11: Inflation Rate | B11: 0.025 | C11: % | D11: CPI assumption
A12: SCENARIO SELECTOR
A13: Parameter | B13: Value | C13: Unit | D13: Notes
A14: Selected Scenario | B14: 2 | C14: 1-3 | D14: 1=Bear 2=Base 3=Bull
A15: Bear Growth Rate | B15: 0.03 | C15: % | D15: Pessimistic case
A16: Base Growth Rate | B16: 0.08 | C16: % | D16: Central case
A17: Bull Growth Rate | B17: 0.15 | C17: % | D17: Optimistic case
A18: Active Growth Rate | B18: =IFERROR(CHOOSE(B14,B15,B16,B17),NA()) -> 0.08 | C18: % | D18: CHOOSE picks scenario growth rate

Sheet Revenue Model
A1: 📊 5-Year Revenue & Profit Model
B3: PROJECTED YEARS ($ thousands)
A4: Line Item | B4: 2025 | C4: 2026 | D4: 2027 | E4: 2028 | F4: 2029
A5: Revenue ($000s) | B5: =Assumptions!B5/1000 -> 5000 | C5: =IFERROR(B5*(1+Assumptions!B18),B5*(1+Assumptions!B6)) -> 5400 | D5: =IFERROR(C5*(1+Assumptions!B18),C5*(1+Assumptions!B6)) -> 5832 | E5: =IFERROR(D5*(1+Assumptions!B18),D5*(1+Assumptions!B6)) -> 6298.56 | F5: =IFERROR(E5*(1+Assumptions!B18),E5*(1+Assumptions!B6)) -> 6802.4448
A6: YoY Growth % | B6: =IFERROR(NA(),"-") -> - | C6: =IFERROR((C5-B5)/B5,NA()) -> 0.08 | D6: =IFERROR((D5-C5)/C5,NA()) -> 0.08 | E6: =IFERROR((E5-D5)/D5,NA()) -> 0.08 | F6: =IFERROR((F5-E5)/E5,NA()) -> 0.08
A7: Gross Profit | B7: =B5*Assumptions!$B$7 -> 3100 | C7: =C5*Assumptions!$B$7 -> 3348 | D7: =D5*Assumptions!$B$7 -> 3615.84 | E7: =E5*Assumptions!$B$7 -> 3905.1072 | F7: =F5*Assumptions!$B$7 -> 4217.5158
A8: Gross Margin % | B8: =IFERROR(B7/B5,NA()) -> 0.62 | C8: =IFERROR(C7/C5,NA()) -> 0.62 | D8: =IFERROR(D7/D5,NA()) -> 0.62 | E8: =IFERROR(E7/E5,NA()) -> 0.62 | F8: =IFERROR(F7/F5,NA()) -> 0.62
A9: Operating Expenses | B9: =B5*Assumptions!$B$8 -> 1750 | C9: =C5*Assumptions!$B$8 -> 1890 | D9: =D5*Assumptions!$B$8 -> 2041.2 | E9: =E5*Assumptions!$B$8 -> 2204.496 | F9: =F5*Assumptions!$B$8 -> 2380.8557
A10: EBIT | B10: =B7-B9 -> 1350 | C10: =C7-C9 -> 1458 | D10: =D7-D9 -> 1574.64 | E10: =E7-E9 -> 1700.6112 | F10: =F7-F9 -> 1836.6601
A11: EBIT Margin % | B11: =IFERROR(B10/B5,NA()) -> 0.27 | C11: =IFERROR(C10/C5,NA()) -> 0.27 | D11: =IFERROR(D10/D5,NA()) -> 0.27 | E11: =IFERROR(E10/E5,NA()) -> 0.27 | F11: =IFERROR(F10/F5,NA()) -> 0.27
A12: Tax Expense | B12: =IF(B10>0,B10*Assumptions!$B$9,0) -> 283.5 | C12: =IF(C10>0,C10*Assumptions!$B$9,0) -> 306.18 | D12: =IF(D10>0,D10*Assumptions!$B$9,0) -> 330.6744 | E12: =IF(E10>0,E10*Assumptions!$B$9,0) -> 357.12835 | F12: =IF(F10>0,F10*Assumptions!$B$9,0) -> 385.69862
A13: Net Income | B13: =B10-B12 -> 1066.5 | C13: =C10-C12 -> 1151.82 | D13: =D10-D12 -> 1243.9656 | E13: =E10-E12 -> 1343.4828 | F13: =F10-F12 -> 1450.9615
A14: Net Margin % | B14: =IFERROR(B13/B5,NA()) -> 0.2133 | C14: =IFERROR(C13/C5,NA()) -> 0.2133 | D14: =IFERROR(D13/D5,NA()) -> 0.2133 | E14: =IFERROR(E13/E5,NA()) -> 0.2133 | F14: =IFERROR(F13/F5,NA()) -> 0.2133
A16: SUMMARY STATISTICS
A17: Metric | B17: Value | C17: Formula Used
A18: Total 5-Yr Revenue | B18: =SUM(B5:F5) -> 29333.005 | C18: SUM
A19: Avg Annual Revenue | B19: =AVERAGE(B5:F5) -> 5866.601 | C19: AVERAGE
A20: Avg Net Margin | B20: =IFERROR(AVERAGE(B14:F14),NA()) -> 0.2133 | C20: AVERAGE+IFERROR
A21: NPV of Net Income | B21: =IFERROR(NPV(Assumptions!B10,C13:F13)+B13,NA()) -> 5142.0846 | C21: NPV
A22: Max Revenue Year | B22: =TEXT(INDEX(B4:F4,MATCH(MAX(B5:F5),B5:F5,0)),"0") -> 2029 | C22: INDEX+MATCH+TEXT
A23: Revenue CAGR | B23: =IFERROR((F5/B5)^(1/4)-1,NA()) -> 0.08 | C23: Math
A24: Total Net Income | B24: =SUM(B13:F13) -> 6256.7299 | C24: SUM

Sheet Product Lookup
A1: 🔍 Product Lookup — VLOOKUP / INDEX-MATCH / SUMPRODUCT
A3: PRODUCT MASTER TABLE | H3: DYNAMIC LOOKUP PANEL
A4: Product ID | B4: Product Name | C4: Category | D4: Unit Price | E4: Units Sold | F4: Revenue | H4: Field | I4: Result | J4: Formula | K4: Notes
A5: P001 | B5: Alpha Widget | C5: Hardware | D5: 149.99 | E5: 3200 | F5: =D5*E5 -> 479968 | H5: Lookup Product ID | I5: P003 | J5: Input (Blue)
A6: P002 | B6: Beta Service | C6: Software | D6: 299 | E6: 1500 | F6: =D6*E6 -> 448500 | H6: Product Name (VLOOKUP) | I6: =IFERROR(VLOOKUP(I5,A5:F12,2,FALSE()),"Not Found") -> Gamma Suite | J6: VLOOKUP col 2
A7: P003 | B7: Gamma Suite | C7: Software | D7: 499 | E7: 800 | F7: =D7*E7 -> 399200 | H7: Unit Price (INDEX/MATCH) | I7: =IFERROR(INDEX(D5:D12,MATCH(I5,A5:A12,0)),NA()) -> 499 | J7: INDEX+MATCH
A8: P004 | B8: Delta Device | C8: Hardware | D8: 89.5 | E8: 5600 | F8: =D8*E8 -> 501200 | H8: Units Sold | I8: =IFERROR(INDEX(E5:E12,MATCH(I5,A5:A12,0)),NA()) -> 800 | J8: INDEX+MATCH
A9: P005 | B9: Epsilon Pack | C9: Accessory | D9: 24.99 | E9: 12000 | F9: =D9*E9 -> 299880 | H9: Revenue | I9: =IFERROR(INDEX(F5:F12,MATCH(I5,A5:A12,0)),NA()) -> 399200 | J9: INDEX+MATCH
A10: P006 | B10: Zeta Module | C10: Hardware | D10: 399 | E10: 450 | F10: =D10*E10 -> 179550 | H10: Category | I10: =IFERROR(VLOOKUP(I5,A5:F12,3,FALSE()),"Not Found") -> Software | J10: VLOOKUP col 3
A11: P007 | B11: Eta License | C11: Software | D11: 999 | E11: 200 | F11: =D11*E11 -> 199800 | H11: ID Found? | I11: =IF(ISNUMBER(MATCH(I5,A5:A12,0)),"✔ Found","✘ Not Found") -> ✔ Found | J11: ISNUMBER+MATCH
A12: P008 | B12: Theta Kit | C12: Accessory | D12: 59.99 | E12: 3800 | F12: =D12*E12 -> 227962
A13: TOTALS | E13: =SUM(E5:E12) -> 27550 | F13: =SUM(F5:F12) -> 2736060 | H13: SUMPRODUCT ANALYTICS
H14: SW Revenue (SUMPRODUCT) | I14: =SUMPRODUCT((C5:C12="Software")*F5:F12) -> 1047500 | J14: Sum revenue where category=Software
H15: HW Revenue (SUMPRODUCT) | I15: =SUMPRODUCT((C5:C12="Hardware")*F5:F12) -> 1160718 | J15: Sum revenue where category=Hardware
H16: Accessory Revenue | I16: =SUMPRODUCT((C5:C12="Accessory")*F5:F12) -> 527842 | J16: Sum revenue where category=Accessory
H17: Weighted Avg Price | I17: =IFERROR(SUMPRODUCT(D5:D12,E5:E12)/SUM(E5:E12),NA()) -> 99.312523 | J17: SUMPRODUCT / SUM
H18: Products > $200 price | I18: =SUMPRODUCT((D5:D12>200)*1) -> 4 | J18: Count where price>200
H19: ROW-based running idx | I19: =SUMPRODUCT((ROW(A5:A12)-ROW(A5)+1)*(C5:C12="Software")) -> 12 | J19: ROW inside SUMPRODUCT

Sheet Statistical Analysis
A1: 📈 Statistical Analysis — NORMDIST, OFFSET, AVERAGE, SUMPRODUCT
A3: MONTHLY SALES DATA | E3: DESCRIPTIVE STATISTICS
A4: Month | B4: Sales ($000) | C4: Row Index | E4: Statistic | F4: Value | G4: Formula
A5: Jan | B5: 312 | C5: =ROW()-ROW($C$5)+1 -> 1 | E5: Mean | F5: =AVERAGE(B5:B16) -> 455.16667 | G5: AVERAGE
A6: Feb | B6: 287 | C6: =ROW()-ROW($C$5)+1 -> 2 | E6: Std Dev | F6: =IFERROR(SUMPRODUCT((B5:B16-AVERAGE(B5:B16))^2)/COUNT(B5:B16),NA())^0.5 -> 102.92621 | G6: SUMPRODUCT variance
A7: Mar | B7: 341 | C7: =ROW()-ROW($C$5)+1 -> 3 | E7: Min | F7: =MIN(B5:B16) -> 287 | G7: MIN
A8: Apr | B8: 398 | C8: =ROW()-ROW($C$5)+1 -> 4 | E8: Max | F8: =MAX(B5:B16) -> 628 | G8: MAX
A9: May | B9: 422 | C9: =ROW()-ROW($C$5)+1 -> 5 | E9: Count | F9: =COUNT(B5:B16) -> 12 | G9: COUNT
A10: Jun | B10: 461 | C10: =ROW()-ROW($C$5)+1 -> 6 | E10: Q2 Sales (OFFSET) | F10: =IFERROR(AVERAGE(OFFSET(B5,3,0,3,1)),NA()) -> 427 | G10: OFFSET
A11: Jul | B11: 488 | C11: =ROW()-ROW($C$5)+1 -> 7 | E11: Q4 Sales (OFFSET) | F11: =IFERROR(AVERAGE(OFFSET(B5,9,0,3,1)),NA()) -> 587.33333 | G11: OFFSET
A12: Aug | B12: 512 | C12: =ROW()-ROW($C$5)+1 -> 8 | E12: 3-Mo Moving Avg | F12: =IFERROR(AVERAGE(OFFSET(B16,-2,0,3,1)),NA()) -> 587.33333 | G12: OFFSET trailing
A13: Sep | B13: 479 | C13: =ROW()-ROW($C$5)+1 -> 9
A14: Oct | B14: 543 | C14: =ROW()-ROW($C$5)+1 -> 10 | E14: NORMAL DISTRIBUTION TABLE
A15: Nov | B15: 591 | C15: =ROW()-ROW($C$5)+1 -> 11 | E15: Sales Value | F15: Z-Score | G15: CDF (NORMDIST) | H15: Above Mean?
A16: Dec | B16: 628 | C16: =ROW()-ROW($C$5)+1 -> 12 | E16: =B5 -> 312 | F16: =IFERROR((E16-$F$5)/$F$6,NA()) -> -1.3909641 | G16: =IFERROR(NORMDIST(E16,$F$5,$F$6,TRUE()),NA()) -> 0.08211816 | H16: =IF(ISNUMBER(F16),IF(F16>0,"Above","Below"),"N/A") -> Below
E17: =B6 -> 287 | F17: =IFERROR((E17-$F$5)/$F$6,NA()) -> -1.6338565 | G17: =IFERROR(NORMDIST(E17,$F$5,$F$6,TRUE()),NA()) -> 0.05114449 | H17: =IF(ISNUMBER(F17),IF(F17>0,"Above","Below"),"N/A") -> Below
E18: =B7 -> 341 | F18: =IFERROR((E18-$F$5)/$F$6,NA()) -> -1.1092088 | G18: =IFERROR(NORMDIST(E18,$F$5,$F$6,TRUE()),NA()) -> 0.13367005 | H18: =IF(ISNUMBER(F18),IF(F18>0,"Above","Below"),"N/A") -> Below
E19: =B8 -> 398 | F19: =IFERROR((E19-$F$5)/$F$6,NA()) -> -0.55541406 | G19: =IFERROR(NORMDIST(E19,$F$5,$F$6,TRUE()),NA()) -> 0.28930574 | H19: =IF(ISNUMBER(F19),IF(F19>0,"Above","Below"),"N/A") -> Below
E20: =B9 -> 422 | F20: =IFERROR((E20-$F$5)/$F$6,NA()) -> -0.32223731 | G20: =IFERROR(NORMDIST(E20,$F$5,$F$6,TRUE()),NA()) -> 0.37363646 | H20: =IF(ISNUMBER(F20),IF(F20>0,"Above","Below"),"N/A") -> Below
E21: =B10 -> 461 | F21: =IFERROR((E21-$F$5)/$F$6,NA()) -> 0.056674904 | G21: =IFERROR(NORMDIST(E21,$F$5,$F$6,TRUE()),NA()) -> 0.52259792 | H21: =IF(ISNUMBER(F21),IF(F21>0,"Above","Below"),"N/A") -> Above
E22: =B11 -> 488 | F22: =IFERROR((E22-$F$5)/$F$6,NA()) -> 0.31899875 | G22: =IFERROR(NORMDIST(E22,$F$5,$F$6,TRUE()),NA()) -> 0.62513627 | H22: =IF(ISNUMBER(F22),IF(F22>0,"Above","Below"),"N/A") -> Above
E23: =B12 -> 512 | F23: =IFERROR((E23-$F$5)/$F$6,NA()) -> 0.5521755 | G23: =IFERROR(NORMDIST(E23,$F$5,$F$6,TRUE()),NA()) -> 0.70958594 | H23: =IF(ISNUMBER(F23),IF(F23>0,"Above","Below"),"N/A") -> Above
E24: =B13 -> 479 | F24: =IFERROR((E24-$F$5)/$F$6,NA()) -> 0.23155747 | G24: =IFERROR(NORMDIST(E24,$F$5,$F$6,TRUE()),NA()) -> 0.59155913 | H24: =IF(ISNUMBER(F24),IF(F24>0,"Above","Below"),"N/A") -> Above
E25: =B14 -> 543 | F25: =IFERROR((E25-$F$5)/$F$6,NA()) -> 0.85336213 | G25: =IFERROR(NORMDIST(E25,$F$5,$F$6,TRUE()),NA()) -> 0.80327074 | H25: =IF(ISNUMBER(F25),IF(F25>0,"Above","Below"),"N/A") -> Above
E26: =B15 -> 591 | F26: =IFERROR((E26-$F$5)/$F$6,NA()) -> 1.3197156 | G26: =IFERROR(NORMDIST(E26,$F$5,$F$6,TRUE()),NA()) -> 0.90653501 | H26: =IF(ISNUMBER(F26),IF(F26>0,"Above","Below"),"N/A") -> Above
E27: =B16 -> 628 | F27: =IFERROR((E27-$F$5)/$F$6,NA()) -> 1.6791964 | G27: =IFERROR(NORMDIST(E27,$F$5,$F$6,TRUE()),NA()) -> 0.95344312 | H27: =IF(ISNUMBER(F27),IF(F27>0,"Above","Below"),"N/A") -> Above

Sheet DCF Valuation
A1: 💰 DCF Valuation — NPV, IF, AND, IFERROR, TEXT
A3: DISCOUNTED CASH FLOW MODEL
A4: Item | B4: Year 1 | C4: Year 2 | D4: Year 3 | E4: Year 4
A5: Revenue ($000s) | B5: ='Revenue Model'!B5 -> 5000 | C5: ='Revenue Model'!C5 -> 5400 | D5: ='Revenue Model'!D5 -> 5832 | E5: ='Revenue Model'!E5 -> 6298.56
A6: Net Income ($000s) | B6: ='Revenue Model'!B13 -> 1066.5 | C6: ='Revenue Model'!C13 -> 1151.82 | D6: ='Revenue Model'!D13 -> 1243.9656 | E6: ='Revenue Model'!E13 -> 1343.4828
A7: D&A (2% Rev) | B7: =B5*0.02 -> 100 | C7: =C5*0.02 -> 108 | D7: =D5*0.02 -> 116.64 | E7: =E5*0.02 -> 125.9712
A8: Capex (5% Rev) | B8: =-B5*0.05 -> -250 | C8: =-C5*0.05 -> -270 | D8: =-D5*0.05 -> -291.6 | E8: =-E5*0.05 -> -314.928
A9: Free Cash Flow | B9: =B6+B7+B8 -> 916.5 | C9: =C6+C7+C8 -> 989.82 | D9: =D6+D7+D8 -> 1069.0056 | E9: =E6+E7+E8 -> 1154.526
A11: Discount Rate | B11: =Assumptions!B10 -> 0.1
A12: Discount Factor | B12: =IFERROR(1/(1+$B$11)^1,NA()) -> 0.90909091 | C12: =IFERROR(1/(1+$B$11)^2,NA()) -> 0.82644628 | D12: =IFERROR(1/(1+$B$11)^3,NA()) -> 0.7513148 | E12: =IFERROR(1/(1+$B$11)^4,NA()) -> 0.68301346
A13: PV of FCF | B13: =IF(AND(B9>0,B12>0),B9*B12,B9*B12) -> 833.18182 | C13: =IF(AND(C9>0,C12>0),C9*C12,C9*C12) -> 818.03306 | D13: =IF(AND(D9>0,D12>0),D9*D12,D9*D12) -> 803.15973 | E13: =IF(AND(E9>0,E12>0),E9*E12,E9*E12) -> 788.55683
A16: VALUATION SUMMARY
A17: Metric | B17: Value | C17: Formula
A18: Sum of PV FCFs | B18: =SUM(B13:E13) -> 3242.9314 | C18: SUM
A19: NPV (Excel NPV fn) | B19: =IFERROR(NPV(B11,C9:E9)+B9,NA()) -> 3567.2246 | C19: NPV
A20: Terminal Value | B20: =IFERROR(E9*(1+0.025)/(B11-0.025),NA()) -> 15778.523 | C20: Gordon Growth
A21: PV Terminal Value | B21: =IFERROR(B20/(1+B11)^4,NA()) -> 10776.943 | C21: Math
A22: Enterprise Value | B22: =IFERROR(B18+B21,NA()) -> 14019.875 | C22: Sum
A23: Signal | B23: =IF(AND(B22>0,B18>0),IF(B22>B18*2,"Strong Buy",IF(B22>B18,"Buy","Hold")),"N/A") -> Strong Buy | C23: IF+AND+nested
A24: NPV as TEXT | B24: =IFERROR(TEXT(B18,"$#,##0")&"K","N/A") -> $3,243K | C24: TEXT

Sheet Formula Index
A1: 📚 Formula Reference — All Functions Used in This Workbook
A3: COMPLETE FORMULA REFERENCE
A4: Function | B4: Category | C4: Sheet(s) Used | D4: Purpose | E4: Example
A5: IF | B5: Logical | C5: All | D5: Conditional branching | E5: '=IF(A1>0,"Pos","Neg")
A6: IFERROR | B6: Logical | C6: All | D6: Suppress errors gracefully | E6: '=IFERROR(1/0,"Err")
A7: ISNUMBER | B7: Information | C7: Product Lookup | D7: Check if value is numeric | E7: '=ISNUMBER(MATCH(...))
A8: AND | B8: Logical | C8: DCF Valuation | D8: All conditions must be true | E8: '=AND(A1>0,B1>0)
A9: SUM | B9: Math | C9: Revenue Model | D9: Sum a range | E9: '=SUM(B5:F5)
A10: AVERAGE | B10: Statistical | C10: Revenue, Stats | D10: Mean of range | E10: '=AVERAGE(B5:B16)
A11: SUMPRODUCT | B11: Math | C11: Product Lookup | D11: Array multiply then sum | E11: '=SUMPRODUCT(D5:D12,E5:E12)
A12: NPV | B12: Financial | C12: DCF Valuation | D12: Net present value of cash flows | E12: '=NPV(rate,C9:E9)+B9
A13: CHOOSE | B13: Lookup | C13: Assumptions | D13: Return nth item from list | E13: '=CHOOSE(2,"Bear","Base","Bull")
A14: MATCH | B14: Lookup | C14: Revenue, Lookup | D14: Position of value in range | E14: '=MATCH("P001",A5:A12,0)
A15: INDEX | B15: Lookup | C15: Revenue, Lookup | D15: Value at row/col intersection | E15: '=INDEX(D5:D12,3)
... A21: NA | B21: Information | C21: Revenue, Statistical | D21: Returns the N/A error intentionally | E21: '=NA()
